dfsaas_blog/__init__.py
dfsaas_blog/admin.py
dfsaas_blog/apps.py
dfsaas_blog/managers.py
dfsaas_blog/models.py
dfsaas_blog/tests.py
dfsaas_blog/urls.py
dfsaas_blog/views.py
dfsaas_blog/migrations/0001_initial.py
dfsaas_blog/migrations/__init__.py
dfsaas_blog/templates/dfsaas_blog/base.html
dfsaas_blog/templates/dfsaas_blog/category.html
dfsaas_blog/templates/dfsaas_blog/main.html
dfsaas_blog/templates/dfsaas_blog/post.html
dfsaas_blog/templates/dfsaas_blog/tag.html
tests/__init__.py
tests/settings.py
tests/urls.py
dfsaas_blog-0.1.4.dist-info/LICENCE
dfsaas_blog-0.1.4.dist-info/METADATA
dfsaas_blog-0.1.4.dist-info/WHEEL
dfsaas_blog-0.1.4.dist-info/top_level.txt
dfsaas_blog-0.1.4.dist-info/RECORD
